MANIFEST.in
README.md
setup.py
pipdiff/__init__.py
pipdiff/pipdiff.py
pipdiff.egg-info/PKG-INFO
pipdiff.egg-info/SOURCES.txt
pipdiff.egg-info/dependency_links.txt
pipdiff.egg-info/entry_points.txt
pipdiff.egg-info/not-zip-safe
pipdiff.egg-info/top_level.txt