Metadata-Version: 1.0
Name: pipdiff
Version: 0.2
Summary: View a summary list of package release differences between your local environment and PyPI.
Home-page: https://github.com/ogt/pipdiff
Author: Evgeny Demchenko
Author-email: little_pea@list.ru
License: BSD
Platform: UNKNOWN
